boilersetup/__init__.py
boilersetup-0.9.0.dist-info/LICENSE
boilersetup-0.9.0.dist-info/METADATA
boilersetup-0.9.0.dist-info/WHEEL
boilersetup-0.9.0.dist-info/RECORD
